{
  "id":1,
  "name":"Piazza Mattei",
  "address":"Piazza Mattei, 00186 Roma",
  "desc":"[Piazza Mattei]",
  "latLng":[
    41.893887,
    12.477525
  ],
  "date":1950,
  "pos":763,
  "cat":{
    "id":2,
    "name":"Pasolini Schriftsteller"
  },
  "m":[
    {
      "type":"img",
      "id":"1-1",
      "width":1600,
      "height":1199,
      "caption":"[La Piazza Mattei et sa fontaine des Tortues]",
      "rights":"\u00a9 Archivio Storico Capitolino \u2013 Biblioteca Romana"
    }
  ],
  "trello":"VMcQZ3f7",
  "lang":"de"
}